data_verification/__init__.py
data_verification/gather.py
data_verification/geo/__init__.py
data_verification/geo/geo.py
data_verification/public/__init__.py
data_verification/public/admin_division.py
data_verification/public/compare.py
data_verification/public/coordinates.py
data_verification/public/decode.py
data_verification/public/domain.py
data_verification/public/email.py
data_verification/public/empty.py
data_verification/public/id_number.py
data_verification/public/ip_address.py
data_verification/public/number.py
data_verification/public/organization.py
data_verification/public/phone_number.py
data_verification/public/postal.py
data_verification/public/regex.py
data_verification/public/scc.py
data_verification/public/time.py
data_verification/public/unique.py
data_verification/public/verify_type.py
data_verification-0.0.2.2.dist-info/LICENSE.txt
data_verification-0.0.2.2.dist-info/METADATA
data_verification-0.0.2.2.dist-info/WHEEL
data_verification-0.0.2.2.dist-info/top_level.txt
data_verification-0.0.2.2.dist-info/RECORD
