Metadata-Version: 2.2
Name: data_verification
Version: 0.0.2.2
Summary: 数据检验的工具
Home-page: https://github.com/yanshi121/DataVerification
Author: 39
Author-email: DY39project@outlook.com
Classifier: Programming Language :: Python :: 3
Classifier: License :: OSI Approved :: MIT License
Classifier: Operating System :: Microsoft :: Windows
Classifier: Operating System :: POSIX :: Linux
Requires-Python: >=3.5
License-File: LICENSE.txt
Requires-Dist: geopandas
Requires-Dist: shapely
Dynamic: author
Dynamic: author-email
Dynamic: classifier
Dynamic: description
Dynamic: description-content-type
Dynamic: home-page
Dynamic: requires-dist
Dynamic: requires-python
Dynamic: summary
